LICENSE
MANIFEST.in
README.md
package.json
setup.py
submit_button/SubmitButton.py
submit_button/__init__.py
submit_button/_imports_.py
submit_button/metadata.json
submit_button/package-info.json
submit_button/submit_button.min.js
submit_button/submit_button.min.js.map
submit_button.egg-info/PKG-INFO
submit_button.egg-info/SOURCES.txt
submit_button.egg-info/dependency_links.txt
submit_button.egg-info/top_level.txt