Metadata-Version: 1.1
Name: submit-button
Version: 0.0.1
Summary: the submit button
Home-page: UNKNOWN
Author: kalimuthu periyasamy <1995kalimuthu@gmail.com>
Author-email: UNKNOWN
License: MIT
Platform: UNKNOWN
Classifier: Framework :: Dash
